AutomaticRange/__init__.py
AutomaticRange/data.py
AutomaticRange/models.py
AutomaticRange/smooth.py
AutomaticRange/train.py
AutomaticRange/validate.py
automaticrange-0.1.6.dist-info/licenses/LICENSE
automaticrange-0.1.6.dist-info/METADATA
automaticrange-0.1.6.dist-info/WHEEL
automaticrange-0.1.6.dist-info/top_level.txt
automaticrange-0.1.6.dist-info/RECORD
