Metadata-Version: 2.4
Name: AutomaticRange
Version: 0.1.6
Summary: A python package for automatic range prediction.
Home-page: https://github.com/pacomito/AutomaticRange
Author: Pacôme Prompsy
Author-email: pacome.prompsy@unil.ch
License: GPL-3.0
License-File: LICENSE
Requires-Dist: numpy
Requires-Dist: torch
Requires-Dist: torchvision
Requires-Dist: scipy
Requires-Dist: scikit-image
Requires-Dist: tifffile
Requires-Dist: opencv-python
Dynamic: author
Dynamic: author-email
Dynamic: license-file
Dynamic: requires-dist
Dynamic: summary
